ss_scrapping/__init__.py
ss_scrapping/chromedriver/LICENSE.chromedriver
ss_scrapping/chromedriver/THIRD_PARTY_NOTICES.chromedriver
ss_scrapping/chromedriver/chromedriver
ss_scrapping/topuniversities/__init__.py
ss_scrapping/topuniversities/admission_req.py
ss_scrapping/topuniversities/faculty.py
ss_scrapping/topuniversities/fin_info.py
ss_scrapping/topuniversities/helper.py
ss_scrapping/topuniversities/institution.py
ss_scrapping/topuniversities/metadata.py
ss_scrapping/topuniversities/programs.py
ss_scrapping/topuniversities/rankings.py
ss_scrapping/topuniversities/student.py
ss_scrapping/topuniversities/topuniversities.py
ss_scrapping/topuniversities/utils.py
ss_scrapping/usnews/__init__.py
ss_scrapping/usnews/admission_req.py
ss_scrapping/usnews/after_grad.py
ss_scrapping/usnews/features.py
ss_scrapping/usnews/fin_info.py
ss_scrapping/usnews/helper.py
ss_scrapping/usnews/institution.py
ss_scrapping/usnews/metadata.py
ss_scrapping/usnews/programs.py
ss_scrapping/usnews/rankings.py
ss_scrapping/usnews/student.py
ss_scrapping/usnews/usnews.py
ss_scrapping/usnews/utils.py
ss_scrapping-0.2.dist-info/METADATA
ss_scrapping-0.2.dist-info/WHEEL
ss_scrapping-0.2.dist-info/entry_points.txt
ss_scrapping-0.2.dist-info/top_level.txt
ss_scrapping-0.2.dist-info/RECORD
