Metadata-Version: 2.2
Name: ss-scrapping
Version: 0.2
Summary: A Python package for top 500 universities
Author: Parijat Srivastava
Requires-Dist: absl-py==2.1.0
Requires-Dist: astunparse==1.6.3
Requires-Dist: attrs==24.3.0
Requires-Dist: beautifulsoup4==4.12.3
Requires-Dist: certifi==2024.12.14
Requires-Dist: charset-normalizer==3.4.1
Requires-Dist: filelock==3.16.1
Requires-Dist: flatbuffers==24.12.23
Requires-Dist: fsspec==2024.12.0
Requires-Dist: gast==0.6.0
Requires-Dist: google-pasta==0.2.0
Requires-Dist: grpcio==1.69.0
Requires-Dist: h11==0.14.0
Requires-Dist: h5py==3.12.1
Requires-Dist: huggingface-hub==0.27.1
Requires-Dist: idna==3.10
Requires-Dist: intel-tensorflow==0.0.1
Requires-Dist: Jinja2==3.1.5
Requires-Dist: keras==3.8.0
Requires-Dist: libclang==18.1.1
Requires-Dist: Markdown==3.7
Requires-Dist: markdown-it-py==3.0.0
Requires-Dist: MarkupSafe==3.0.2
Requires-Dist: mdurl==0.1.2
Requires-Dist: ml-dtypes==0.4.1
Requires-Dist: mpmath==1.3.0
Requires-Dist: namex==0.0.8
Requires-Dist: networkx==3.4.2
Requires-Dist: numpy==2.0.2
Requires-Dist: nvidia-cublas-cu12==12.4.5.8
Requires-Dist: nvidia-cuda-cupti-cu12==12.4.127
Requires-Dist: nvidia-cuda-nvrtc-cu12==12.4.127
Requires-Dist: nvidia-cuda-runtime-cu12==12.4.127
Requires-Dist: nvidia-cudnn-cu12==9.1.0.70
Requires-Dist: nvidia-cufft-cu12==11.2.1.3
Requires-Dist: nvidia-curand-cu12==10.3.5.147
Requires-Dist: nvidia-cusolver-cu12==11.6.1.9
Requires-Dist: nvidia-cusparse-cu12==12.3.1.170
Requires-Dist: nvidia-nccl-cu12==2.21.5
Requires-Dist: nvidia-nvjitlink-cu12==12.4.127
Requires-Dist: nvidia-nvtx-cu12==12.4.127
Requires-Dist: opt_einsum==3.4.0
Requires-Dist: optree==0.13.1
Requires-Dist: outcome==1.3.0.post0
Requires-Dist: packaging==24.2
Requires-Dist: pillow==11.1.0
Requires-Dist: pip-autoremove==0.10.0
Requires-Dist: protobuf==5.29.3
Requires-Dist: Pygments==2.19.1
Requires-Dist: PySocks==1.7.1
Requires-Dist: python-dotenv==1.0.1
Requires-Dist: PyYAML==6.0.2
Requires-Dist: regex==2024.11.6
Requires-Dist: requests==2.32.3
Requires-Dist: rich==13.9.4
Requires-Dist: safetensors==0.5.2
Requires-Dist: selenium==4.27.1
Requires-Dist: setuptools==75.8.0
Requires-Dist: six==1.17.0
Requires-Dist: sniffio==1.3.1
Requires-Dist: sortedcontainers==2.4.0
Requires-Dist: soupsieve==2.6
Requires-Dist: sympy==1.13.1
Requires-Dist: tabulate==0.9.0
Requires-Dist: tensorboard==2.18.0
Requires-Dist: tensorboard-data-server==0.7.2
Requires-Dist: tensorflow==2.18.0
Requires-Dist: termcolor==2.5.0
Requires-Dist: tf_keras==2.18.0
Requires-Dist: tokenizers==0.21.0
Requires-Dist: torch==2.5.1
Requires-Dist: torchaudio==2.5.1
Requires-Dist: torchvision==0.20.1
Requires-Dist: tqdm==4.67.1
Requires-Dist: transformers==4.48.0
Requires-Dist: trio==0.28.0
Requires-Dist: trio-websocket==0.11.1
Requires-Dist: triton==3.1.0
Requires-Dist: typing_extensions==4.12.2
Requires-Dist: urllib3==2.3.0
Requires-Dist: websocket-client==1.8.0
Requires-Dist: Werkzeug==3.1.3
Requires-Dist: wheel==0.45.1
Requires-Dist: wrapt==1.17.1
Requires-Dist: wsproto==1.2.0
Dynamic: author
Dynamic: requires-dist
Dynamic: summary
